tiebameow/__init__.py
tiebameow/py.typed
tiebameow/client/__init__.py
tiebameow/client/http_client.py
tiebameow/client/tieba_client.py
tiebameow/models/__init__.py
tiebameow/models/dto.py
tiebameow/models/orm.py
tiebameow/parser/__init__.py
tiebameow/parser/parser.py
tiebameow/parser/rule_parser.py
tiebameow/renderer/__init__.py
tiebameow/renderer/config.py
tiebameow/renderer/playwright_core.py
tiebameow/renderer/renderer.py
tiebameow/renderer/style.py
tiebameow/renderer/static/fonts/NotoSansSC-Regular.woff2
tiebameow/renderer/templates/base.html
tiebameow/renderer/templates/macros.html
tiebameow/renderer/templates/text.html
tiebameow/renderer/templates/text_simple.html
tiebameow/renderer/templates/thread.html
tiebameow/renderer/templates/thread_detail.html
tiebameow/renderer/templates/thread_info.html
tiebameow/schemas/__init__.py
tiebameow/schemas/fragments.py
tiebameow/schemas/rules.py
tiebameow/serializer/__init__.py
tiebameow/serializer/serializer.py
tiebameow/utils/__init__.py
tiebameow/utils/logger.py
tiebameow/utils/time_utils.py
tiebameow-0.2.10.dist-info/METADATA
tiebameow-0.2.10.dist-info/WHEEL
tiebameow-0.2.10.dist-info/licenses/LICENSE
tiebameow-0.2.10.dist-info/RECORD
