Metadata-Version: 2.4
Name: tiebameow
Version: 0.2.10
Summary: Shared library for TiebaMeow services
License-Expression: MIT
License-File: LICENSE
Keywords: tieba
Classifier: License :: OSI Approved :: MIT License
Classifier: Programming Language :: Python
Classifier: Programming Language :: Python :: 3
Classifier: Programming Language :: Python :: 3.12
Classifier: Programming Language :: Python :: 3.13
Classifier: Programming Language :: Python :: 3.14
Requires-Python: >=3.12
Requires-Dist: aiolimiter>=1.2.1
Requires-Dist: aiotieba>=4.6.1
Requires-Dist: httpx>=0.28.1
Requires-Dist: loguru>=0.7.3
Requires-Dist: pydantic>=2.12.5
Requires-Dist: pyparsing>=3.3.1
Requires-Dist: tenacity>=9.1.2
Requires-Dist: tzdata>=2025.2
Provides-Extra: orm
Requires-Dist: sqlalchemy>=2.0.44; extra == 'orm'
Provides-Extra: renderer
Requires-Dist: jinja2>=3.1.5; extra == 'renderer'
Requires-Dist: playwright>=1.49.1; extra == 'renderer'
